[
	{
		"Name": "NewRow",
		"DialogueChainID": "d_tut01_d1",
		"DialogueID": "001",
		"DialogueType": "Dialogue",
		"DialogueText": "This is the tutorial.",
		"Action": "PlayerNext",
		"DialogueSpeaker": "NPC",
		"SpeakerName": "NSLOCTEXT(\"[972A3964A41D1CFCB3B9287095DCF6F6]\", \"5D0598AF45D79F78683E928B33CDB3B7\", \"Man 1\")",
		"ChoicesAmount": 0,
		"ChoiceIndex": 0,
		"DialogueTags":
		{
			"GameplayTags": [],
			"ParentTags": []
		}
	},
	{
		"Name": "NewRow_0",
		"DialogueChainID": "d_tut01_d1",
		"DialogueID": "002",
		"DialogueType": "Dialogue",
		"DialogueText": "Wow!",
		"Action": "End",
		"DialogueSpeaker": "Player",
		"SpeakerName": "",
		"ChoicesAmount": 0,
		"ChoiceIndex": 0,
		"DialogueTags":
		{
			"GameplayTags": [],
			"ParentTags": []
		}
	},
	{
		"Name": "NewRow_1",
		"DialogueChainID": "d_tut01_d2",
		"DialogueID": "001",
		"DialogueType": "Dialogue",
		"DialogueText": "And this is the second.",
		"Action": "End",
		"DialogueSpeaker": "NPC",
		"SpeakerName": "NSLOCTEXT(\"[972A3964A41D1CFCB3B9287095DCF6F6]\", \"73D2F5B74674B259860A3CA50A20B6FE\", \"Man 2\")",
		"ChoicesAmount": 0,
		"ChoiceIndex": 0,
		"DialogueTags":
		{
			"GameplayTags": [],
			"ParentTags": []
		}
	},
	{
		"Name": "NewRow_2",
		"DialogueChainID": "d_tut02_d1",
		"DialogueID": "001",
		"DialogueType": "Dialogue",
		"DialogueText": "Wow even the store has a cutscene bro.",
		"Action": "End",
		"DialogueSpeaker": "Player",
		"SpeakerName": "NSLOCTEXT(\"[972A3964A41D1CFCB3B9287095DCF6F6]\", \"3D172E2D4E889F8FCBC7E7B2FDC2E0D8\", \"You\")",
		"ChoicesAmount": 0,
		"ChoiceIndex": 0,
		"DialogueTags":
		{
			"GameplayTags": [],
			"ParentTags": []
		}
	}
]